mathieumaes_picsou/__init__.py
mathieumaes_picsou/picsou.py
mathieumaes_picsou-0.1.0.dist-info/METADATA
mathieumaes_picsou-0.1.0.dist-info/WHEEL
mathieumaes_picsou-0.1.0.dist-info/RECORD
